{
    "1970004": {
        "province": "青海",
        "city": "海南",
        "isp": "移动"
    },
    "1970005": {
        "province": "青海",
        "city": "果洛",
        "isp": "移动"
    },
    "1970006": {
        "province": "青海",
        "city": "玉树",
        "isp": "移动"
    },
    "1970007": {
        "province": "青海",
        "city": "海西",
        "isp": "移动"
    },
    "1970009": {
        "province": "青海",
        "city": "格尔木",
        "isp": "移动"
    },
    "1970014": {
        "province": "广东",
        "city": "广州",
        "isp": "移动"
    },
    "1970020": {
        "province": "广东",
        "city": "广州",
        "isp": "移动"
    },
    "1970028": {
        "province": "广东",
        "city": "广州",
        "isp": "移动"
    },
    "1970029": {
        "province": "广东",
        "city": "广州",
        "isp": "移动"
    },
    "1970031": {
        "province": "广东",
        "city": "广州",
        "isp": "移动"
    },
    "1970033": {
        "province": "广东",
        "city": "广州",
        "isp": "移动"
    },
    "1970034": {
        "province": "广东",
        "city": "广州",
        "isp": "移动"
    },
    "1970036": {
        "province": "广东",
        "city": "广州",
        "isp": "移动"
    },
    "1970038": {
        "province": "广东",
        "city": "广州",
        "isp": "移动"
    },
    "1970070": {
        "province": "浙江",
        "city": "杭州",
        "isp": "移动"
    },
    "1970071": {
        "province": "浙江",
        "city": "杭州",
        "isp": "移动"
    },
    "1970072": {
        "province": "浙江",
        "city": "杭州",
        "isp": "移动"
    },
    "1970073": {
        "province": "浙江",
        "city": "杭州",
        "isp": "移动"
    },
    "1970074": {
        "province": "浙江",
        "city": "杭州",
        "isp": "移动"
    },
    "1970075": {
        "province": "浙江",
        "city": "杭州",
        "isp": "移动"
    },
    "1970076": {
        "province": "浙江",
        "city": "杭州",
        "isp": "移动"
    },
    "1970077": {
        "province": "浙江",
        "city": "杭州",
        "isp": "移动"
    },
    "1970078": {
        "province": "浙江",
        "city": "杭州",
        "isp": "移动"
    },
    "1970079": {
        "province": "浙江",
        "city": "杭州",
        "isp": "移动"
    },
    "1970092": {
        "province": "浙江",
        "city": "金华",
        "isp": "移动"
    },
    "1970093": {
        "province": "浙江",
        "city": "金华",
        "isp": "移动"
    },
    "1970117": {
        "province": "浙江",
        "city": "金华",
        "isp": "移动"
    },
    "1970119": {
        "province": "江苏",
        "city": "宿迁",
        "isp": "移动"
    },
    "1970121": {
        "province": "江苏",
        "city": "宿迁",
        "isp": "移动"
    },
    "1970122": {
        "province": "江苏",
        "city": "宿迁",
        "isp": "移动"
    },
    "1970123": {
        "province": "江苏",
        "city": "宿迁",
        "isp": "移动"
    },
    "1970125": {
        "province": "江苏",
        "city": "宿迁",
        "isp": "移动"
    },
    "1970126": {
        "province": "江苏",
        "city": "宿迁",
        "isp": "移动"
    },
    "1970127": {
        "province": "江苏",
        "city": "宿迁",
        "isp": "移动"
    },
    "1970167": {
        "province": "广东",
        "city": "珠海",
        "isp": "移动"
    },
    "1970170": {
        "province": "广东",
        "city": "珠海",
        "isp": "移动"
    },
    "1970171": {
        "province": "广东",
        "city": "珠海",
        "isp": "移动"
    },
    "1970185": {
        "province": "广东",
        "city": "江门",
        "isp": "移动"
    },
    "1970227": {
        "province": "江苏",
        "city": "南通",
        "isp": "移动"
    },
    "1970229": {
        "province": "江苏",
        "city": "南通",
        "isp": "移动"
    },
    "1970248": {
        "province": "广东",
        "city": "揭阳",
        "isp": "移动"
    },
    "1970276": {
        "province": "广东",
        "city": "揭阳",
        "isp": "移动"
    },
    "1970277": {
        "province": "广东",
        "city": "揭阳",
        "isp": "移动"
    },
    "1970278": {
        "province": "广东",
        "city": "揭阳",
        "isp": "移动"
    },
    "1970279": {
        "province": "广东",
        "city": "揭阳",
        "isp": "移动"
    },
    "1970292": {
        "province": "广东",
        "city": "揭阳",
        "isp": "移动"
    },
    "1970293": {
        "province": "广东",
        "city": "揭阳",
        "isp": "移动"
    },
    "1970309": {
        "province": "浙江",
        "city": "衢州",
        "isp": "移动"
    },
    "1970310": {
        "province": "河北",
        "city": "邯郸",
        "isp": "移动"
    },
    "1970314": {
        "province": "河北",
        "city": "承德",
        "isp": "移动"
    },
    "1970321": {
        "province": "浙江",
        "city": "湖州",
        "isp": "移动"
    },
    "1970323": {
        "province": "浙江",
        "city": "湖州",
        "isp": "移动"
    },
    "1970328": {
        "province": "浙江",
        "city": "湖州",
        "isp": "移动"
    },
    "1970329": {
        "province": "浙江",
        "city": "湖州",
        "isp": "移动"
    },
    "1970331": {
        "province": "江苏",
        "city": "徐州",
        "isp": "移动"
    },
    "1970332": {
        "province": "江苏",
        "city": "徐州",
        "isp": "移动"
    },
    "1970337": {
        "province": "江苏",
        "city": "徐州",
        "isp": "移动"
    },
    "1970338": {
        "province": "江苏",
        "city": "徐州",
        "isp": "移动"
    },
    "1970355": {
        "province": "山西",
        "city": "长治",
        "isp": "移动"
    },
    "1970356": {
        "province": "山西",
        "city": "晋城",
        "isp": "移动"
    },
    "1970365": {
        "province": "浙江",
        "city": "杭州",
        "isp": "移动"
    },
    "1970367": {
        "province": "浙江",
        "city": "衢州",
        "isp": "移动"
    },
    "1970368": {
        "province": "安徽",
        "city": "宣城",
        "isp": "移动"
    },
    "1970369": {
        "province": "浙江",
        "city": "衢州",
        "isp": "移动"
    },
    "1970380": {
        "province": "浙江",
        "city": "丽水",
        "isp": "移动"
    },
    "1970381": {
        "province": "浙江",
        "city": "丽水",
        "isp": "移动"
    },
    "1970382": {
        "province": "浙江",
        "city": "丽水",
        "isp": "移动"
    },
    "1970383": {
        "province": "浙江",
        "city": "嘉兴",
        "isp": "移动"
    },
    "1970385": {
        "province": "浙江",
        "city": "嘉兴",
        "isp": "移动"
    },
    "1970386": {
        "province": "浙江",
        "city": "嘉兴",
        "isp": "移动"
    },
    "1970389": {
        "province": "浙江",
        "city": "嘉兴",
        "isp": "移动"
    },
    "1970393": {
        "province": "河南",
        "city": "濮阳",
        "isp": "移动"
    },
    "1970399": {
        "province": "浙江",
        "city": "宁波",
        "isp": "移动"
    },
    "1970443": {
        "province": "广东",
        "city": "广州",
        "isp": "移动"
    },
    "1970446": {
        "province": "广东",
        "city": "阳江",
        "isp": "移动"
    },
    "1970465": {
        "province": "浙江",
        "city": "衢州",
        "isp": "移动"
    },
    "1970480": {
        "province": "浙江",
        "city": "宁波",
        "isp": "移动"
    },
    "1970482": {
        "province": "浙江",
        "city": "宁波",
        "isp": "移动"
    },
    "1970491": {
        "province": "浙江",
        "city": "温州",
        "isp": "移动"
    },
    "1970492": {
        "province": "浙江",
        "city": "温州",
        "isp": "移动"
    },
    "1970500": {
        "province": "浙江",
        "city": "杭州",
        "isp": "移动"
    },
    "1970501": {
        "province": "浙江",
        "city": "杭州",
        "isp": "移动"
    },
    "1970502": {
        "province": "浙江",
        "city": "杭州",
        "isp": "移动"
    },
    "1970505": {
        "province": "浙江",
        "city": "杭州",
        "isp": "移动"
    },
    "1970506": {
        "province": "浙江",
        "city": "杭州",
        "isp": "移动"
    },
    "1970507": {
        "province": "浙江",
        "city": "杭州",
        "isp": "移动"
    },
    "1970509": {
        "province": "浙江",
        "city": "杭州",
        "isp": "移动"
    },
    "1970511": {
        "province": "江苏",
        "city": "盐城",
        "isp": "移动"
    },
    "1970516": {
        "province": "江苏",
        "city": "南京",
        "isp": "移动"
    },
    "1970517": {
        "province": "江苏",
        "city": "南京",
        "isp": "移动"
    },
    "1970518": {
        "province": "江苏",
        "city": "南京",
        "isp": "移动"
    },
    "1970520": {
        "province": "浙江",
        "city": "温州",
        "isp": "移动"
    },
    "1970548": {
        "province": "浙江",
        "city": "杭州",
        "isp": "移动"
    },
    "1970549": {
        "province": "浙江",
        "city": "杭州",
        "isp": "移动"
    },
    "1970551": {
        "province": "广东",
        "city": "阳江",
        "isp": "移动"
    },
    "1970558": {
        "province": "广东",
        "city": "揭阳",
        "isp": "移动"
    },
    "1970607": {
        "province": "浙江",
        "city": "温州",
        "isp": "移动"
    },
    "1970610": {
        "province": "浙江",
        "city": "嘉兴",
        "isp": "移动"
    },
    "1970611": {
        "province": "浙江",
        "city": "嘉兴",
        "isp": "移动"
    },
    "1970612": {
        "province": "浙江",
        "city": "嘉兴",
        "isp": "移动"
    },
    "1970613": {
        "province": "浙江",
        "city": "嘉兴",
        "isp": "移动"
    },
    "1970615": {
        "province": "浙江",
        "city": "嘉兴",
        "isp": "移动"
    },
    "1970616": {
        "province": "浙江",
        "city": "嘉兴",
        "isp": "移动"
    },
    "1970618": {
        "province": "浙江",
        "city": "嘉兴",
        "isp": "移动"
    },
    "1970619": {
        "province": "浙江",
        "city": "嘉兴",
        "isp": "移动"
    },
    "1970627": {
        "province": "浙江",
        "city": "绍兴",
        "isp": "移动"
    },
    "1970633": {
        "province": "山东",
        "city": "日照",
        "isp": "移动"
    },
    "1970681": {
        "province": "浙江",
        "city": "杭州",
        "isp": "移动"
    },
    "1970682": {
        "province": "浙江",
        "city": "杭州",
        "isp": "移动"
    },
    "1970683": {
        "province": "浙江",
        "city": "杭州",
        "isp": "移动"
    },
    "1970684": {
        "province": "浙江",
        "city": "杭州",
        "isp": "移动"
    },
    "1970686": {
        "province": "浙江",
        "city": "杭州",
        "isp": "移动"
    },
    "1970687": {
        "province": "浙江",
        "city": "杭州",
        "isp": "移动"
    },
    "1970689": {
        "province": "浙江",
        "city": "杭州",
        "isp": "移动"
    },
    "1970693": {
        "province": "浙江",
        "city": "嘉兴",
        "isp": "移动"
    },
    "1970694": {
        "province": "浙江",
        "city": "嘉兴",
        "isp": "移动"
    },
    "1970696": {
        "province": "浙江",
        "city": "嘉兴",
        "isp": "移动"
    },
    "1970699": {
        "province": "江苏",
        "city": "常州",
        "isp": "移动"
    },
    "1970700": {
        "province": "山东",
        "city": "济南",
        "isp": "移动"
    },
    "1970702": {
        "province": "山东",
        "city": "济南",
        "isp": "移动"
    },
    "1970709": {
        "province": "山东",
        "city": "济南",
        "isp": "移动"
    },
    "1970715": {
        "province": "湖北",
        "city": "咸宁",
        "isp": "移动"
    },
    "1970720": {
        "province": "江苏",
        "city": "镇江",
        "isp": "移动"
    },
    "1970721": {
        "province": "江苏",
        "city": "镇江",
        "isp": "移动"
    },
    "1970725": {
        "province": "江苏",
        "city": "连云港",
        "isp": "移动"
    },
    "1970726": {
        "province": "江苏",
        "city": "连云港",
        "isp": "移动"
    },
    "1970731": {
        "province": "湖南",
        "city": "长沙",
        "isp": "移动"
    },
    "1970735": {
        "province": "湖南",
        "city": "郴州",
        "isp": "移动"
    },
    "1970770": {
        "province": "山东",
        "city": "青岛",
        "isp": "移动"
    },
    "1970771": {
        "province": "山东",
        "city": "青岛",
        "isp": "移动"
    },
    "1970780": {
        "province": "江苏",
        "city": "泰州",
        "isp": "移动"
    },
    "1970793": {
        "province": "江西",
        "city": "上饶",
        "isp": "移动"
    },
    "1970810": {
        "province": "江苏",
        "city": "宿迁",
        "isp": "移动"
    },
    "1970815": {
        "province": "江苏",
        "city": "宿迁",
        "isp": "移动"
    },
    "1970819": {
        "province": "江苏",
        "city": "泰州",
        "isp": "移动"
    },
    "1970821": {
        "province": "江苏",
        "city": "泰州",
        "isp": "移动"
    },
    "1970824": {
        "province": "浙江",
        "city": "丽水",
        "isp": "移动"
    },
    "1970829": {
        "province": "江苏",
        "city": "无锡",
        "isp": "移动"
    },
    "1970831": {
        "province": "四川",
        "city": "成都",
        "isp": "移动"
    },
    "1970839": {
        "province": "四川",
        "city": "达州",
        "isp": "移动"
    },
    "1970840": {
        "province": "江苏",
        "city": "徐州",
        "isp": "移动"
    },
    "1970842": {
        "province": "江苏",
        "city": "南通",
        "isp": "移动"
    },
    "1970844": {
        "province": "江苏",
        "city": "南京",
        "isp": "移动"
    },
    "1970850": {
        "province": "江苏",
        "city": "常州",
        "isp": "移动"
    },
    "1970860": {
        "province": "江苏",
        "city": "无锡",
        "isp": "移动"
    },
    "1970862": {
        "province": "江苏",
        "city": "徐州",
        "isp": "移动"
    },
    "1970865": {
        "province": "江苏",
        "city": "盐城",
        "isp": "移动"
    },
    "1970869": {
        "province": "江苏",
        "city": "盐城",
        "isp": "移动"
    },
    "1970870": {
        "province": "云南",
        "city": "昭通",
        "isp": "移动"
    },
    "1970872": {
        "province": "云南",
        "city": "大理",
        "isp": "移动"
    },
    "1970874": {
        "province": "云南",
        "city": "曲靖",
        "isp": "移动"
    },
    "1970876": {
        "province": "云南",
        "city": "文山",
        "isp": "移动"
    },
    "1970877": {
        "province": "云南",
        "city": "玉溪",
        "isp": "移动"
    },
    "1970878": {
        "province": "云南",
        "city": "楚雄",
        "isp": "移动"
    },
    "1970879": {
        "province": "云南",
        "city": "普洱",
        "isp": "移动"
    },
    "1970895": {
        "province": "江苏",
        "city": "淮安",
        "isp": "移动"
    },
    "1970897": {
        "province": "江苏",
        "city": "淮安",
        "isp": "移动"
    },
    "1970903": {
        "province": "新疆",
        "city": "伊犁",
        "isp": "移动"
    },
    "1970907": {
        "province": "江苏",
        "city": "南京",
        "isp": "移动"
    },
    "1970922": {
        "province": "江苏",
        "city": "南通",
        "isp": "移动"
    },
    "1970924": {
        "province": "江苏",
        "city": "南通",
        "isp": "移动"
    },
    "1970929": {
        "province": "江苏",
        "city": "南通",
        "isp": "移动"
    },
    "1970936": {
        "province": "甘肃",
        "city": "张掖",
        "isp": "移动"
    },
    "1970940": {
        "province": "江苏",
        "city": "连云港",
        "isp": "移动"
    },
    "1970949": {
        "province": "江苏",
        "city": "宿迁",
        "isp": "移动"
    },
    "1970956": {
        "province": "江苏",
        "city": "盐城",
        "isp": "移动"
    },
    "1970960": {
        "province": "山东",
        "city": "潍坊",
        "isp": "移动"
    },
    "1970962": {
        "province": "山东",
        "city": "潍坊",
        "isp": "移动"
    },
    "1970963": {
        "province": "山东",
        "city": "潍坊",
        "isp": "移动"
    },
    "1970965": {
        "province": "山东",
        "city": "潍坊",
        "isp": "移动"
    },
    "1970967": {
        "province": "山东",
        "city": "潍坊",
        "isp": "移动"
    },
    "1970970": {
        "province": "青海",
        "city": "海北",
        "isp": "移动"
    },
    "1970972": {
        "province": "青海",
        "city": "海东",
        "isp": "移动"
    },
    "1970973": {
        "province": "青海",
        "city": "黄南",
        "isp": "移动"
    },
    "1970974": {
        "province": "青海",
        "city": "海南",
        "isp": "移动"
    },
    "1970975": {
        "province": "青海",
        "city": "果洛",
        "isp": "移动"
    },
    "1970976": {
        "province": "青海",
        "city": "玉树",
        "isp": "移动"
    },
    "1970977": {
        "province": "青海",
        "city": "海西",
        "isp": "移动"
    },
    "1970980": {
        "province": "山东",
        "city": "临沂",
        "isp": "移动"
    },
    "1970981": {
        "province": "山东",
        "city": "临沂",
        "isp": "移动"
    },
    "1970983": {
        "province": "山东",
        "city": "临沂",
        "isp": "移动"
    },
    "1970985": {
        "province": "山东",
        "city": "临沂",
        "isp": "移动"
    },
    "1970990": {
        "province": "江苏",
        "city": "徐州",
        "isp": "移动"
    },
    "1970993": {
        "province": "江苏",
        "city": "徐州",
        "isp": "移动"
    },
    "1970999": {
        "province": "山东",
        "city": "济南",
        "isp": "移动"
    },
    "1971008": {
        "province": "河南",
        "city": "郑州",
        "isp": "移动"
    },
    "1971011": {
        "province": "山东",
        "city": "菏泽",
        "isp": "移动"
    },
    "1971013": {
        "province": "山东",
        "city": "菏泽",
        "isp": "移动"
    },
    "1971014": {
        "province": "江苏",
        "city": "南京",
        "isp": "移动"
    },
    "1971015": {
        "province": "山东",
        "city": "菏泽",
        "isp": "移动"
    },
    "1971016": {
        "province": "山东",
        "city": "菏泽",
        "isp": "移动"
    },
    "1971017": {
        "province": "山东",
        "city": "菏泽",
        "isp": "移动"
    },
    "1971019": {
        "province": "山东",
        "city": "菏泽",
        "isp": "移动"
    },
    "1971021": {
        "province": "上海",
        "city": "上海",
        "isp": "移动"
    },
    "1971028": {
        "province": "四川",
        "city": "达州",
        "isp": "移动"
    },
    "1971029": {
        "province": "陕西",
        "city": "西安",
        "isp": "移动"
    },
    "1971036": {
        "province": "山东",
        "city": "威海",
        "isp": "移动"
    },
    "1971037": {
        "province": "河南",
        "city": "南阳",
        "isp": "移动"
    },
    "1971040": {
        "province": "江苏",
        "city": "南京",
        "isp": "移动"
    },
    "1971043": {
        "province": "江苏",
        "city": "苏州",
        "isp": "移动"
    },
    "1971049": {
        "province": "江苏",
        "city": "南通",
        "isp": "移动"
    },
    "1971051": {
        "province": "江苏",
        "city": "镇江",
        "isp": "移动"
    },
    "1971053": {
        "province": "山东",
        "city": "青岛",
        "isp": "移动"
    },
    "1971055": {
        "province": "安徽",
        "city": "马鞍山",
        "isp": "移动"
    },
    "1971058": {
        "province": "浙江",
        "city": "金华",
        "isp": "移动"
    },
    "1971069": {
        "province": "云南",
        "city": "怒江",
        "isp": "移动"
    },
    "1971073": {
        "province": "湖南",
        "city": "长沙",
        "isp": "移动"
    },
    "1971078": {
        "province": "山东",
        "city": "日照",
        "isp": "移动"
    },
    "1971081": {
        "province": "四川",
        "city": "达州",
        "isp": "移动"
    },
    "1971082": {
        "province": "四川",
        "city": "达州",
        "isp": "移动"
    },
    "1971084": {
        "province": "江苏",
        "city": "盐城",
        "isp": "移动"
    },
    "1971088": {
        "province": "云南",
        "city": "丽江",
        "isp": "移动"
    },
    "1971089": {
        "province": "山东",
        "city": "日照",
        "isp": "移动"
    },
    "1971097": {
        "province": "青海",
        "city": "海北",
        "isp": "移动"
    },
    "1971098": {
        "province": "山东",
        "city": "青岛",
        "isp": "移动"
    },
    "1971100": {
        "province": "河南",
        "city": "驻马店",
        "isp": "移动"
    },
    "1971101": {
        "province": "河南",
        "city": "驻马店",
        "isp": "移动"
    },
    "1971103": {
        "province": "河南",
        "city": "驻马店",
        "isp": "移动"
    },
    "1971104": {
        "province": "河南",
        "city": "驻马店",
        "isp": "移动"
    },
    "1971105": {
        "province": "河南",
        "city": "驻马店",
        "isp": "移动"
    },
    "1971117": {
        "province": "江苏",
        "city": "徐州",
        "isp": "移动"
    },
    "1971119": {
        "province": "江苏",
        "city": "徐州",
        "isp": "移动"
    },
    "1971121": {
        "province": "河南",
        "city": "商丘",
        "isp": "移动"
    },
    "1971123": {
        "province": "河南",
        "city": "商丘",
        "isp": "移动"
    },
    "1971125": {
        "province": "河南",
        "city": "商丘",
        "isp": "移动"
    },
    "1971126": {
        "province": "河南",
        "city": "商丘",
        "isp": "移动"
    },
    "1971127": {
        "province": "河南",
        "city": "商丘",
        "isp": "移动"
    },
    "1971128": {
        "province": "河南",
        "city": "商丘",
        "isp": "移动"
    },
    "1971130": {
        "province": "河南",
        "city": "平顶山",
        "isp": "移动"
    },
    "1971135": {
        "province": "广西",
        "city": "贵港",
        "isp": "移动"
    },
    "1971140": {
        "province": "江苏",
        "city": "苏州",
        "isp": "移动"
    },
    "1971159": {
        "province": "广西",
        "city": "北海",
        "isp": "移动"
    },
    "1971160": {
        "province": "广西",
        "city": "钦州",
        "isp": "移动"
    },
    "1971165": {
        "province": "云南",
        "city": "昆明",
        "isp": "移动"
    },
    "1971174": {
        "province": "云南",
        "city": "大理",
        "isp": "移动"
    },
    "1971175": {
        "province": "云南",
        "city": "大理",
        "isp": "移动"
    },
    "1971183": {
        "province": "云南",
        "city": "红河",
        "isp": "移动"
    },
    "1971184": {
        "province": "云南",
        "city": "红河",
        "isp": "移动"
    },
    "1971185": {
        "province": "云南",
        "city": "红河",
        "isp": "移动"
    },
    "1971186": {
        "province": "云南",
        "city": "红河",
        "isp": "移动"
    },
    "1971188": {
        "province": "河北",
        "city": "保定",
        "isp": "移动"
    },
    "1971192": {
        "province": "河北",
        "city": "石家庄",
        "isp": "移动"
    },
    "1971193": {
        "province": "河北",
        "city": "石家庄",
        "isp": "移动"
    },
    "1971201": {
        "province": "山东",
        "city": "烟台",
        "isp": "移动"
    },
    "1971202": {
        "province": "山东",
        "city": "烟台",
        "isp": "移动"
    },
    "1971203": {
        "province": "山东",
        "city": "烟台",
        "isp": "移动"
    },
    "1971204": {
        "province": "江苏",
        "city": "南通",
        "isp": "移动"
    },
    "1971212": {
        "province": "山东",
        "city": "济宁",
        "isp": "移动"
    },
    "1971213": {
        "province": "山东",
        "city": "济宁",
        "isp": "移动"
    },
    "1971215": {
        "province": "山东",
        "city": "济宁",
        "isp": "移动"
    },
    "1971221": {
        "province": "河北",
        "city": "承德",
        "isp": "移动"
    },
    "1971226": {
        "province": "安徽",
        "city": "芜湖",
        "isp": "移动"
    },
    "1971228": {
        "province": "安徽",
        "city": "芜湖",
        "isp": "移动"
    },
    "1971230": {
        "province": "安徽",
        "city": "亳州",
        "isp": "移动"
    },
    "1971231": {
        "province": "安徽",
        "city": "亳州",
        "isp": "移动"
    },
    "1971233": {
        "province": "安徽",
        "city": "亳州",
        "isp": "移动"
    },
    "1971234": {
        "province": "安徽",
        "city": "亳州",
        "isp": "移动"
    },
    "1971235": {
        "province": "安徽",
        "city": "亳州",
        "isp": "移动"
    },
    "1971236": {
        "province": "安徽",
        "city": "亳州",
        "isp": "移动"
    },
    "1971238": {
        "province": "安徽",
        "city": "亳州",
        "isp": "移动"
    },
    "1971245": {
        "province": "江苏",
        "city": "宿迁",
        "isp": "移动"
    },
    "1971252": {
        "province": "河南",
        "city": "新乡",
        "isp": "移动"
    },
    "1971253": {
        "province": "河南",
        "city": "新乡",
        "isp": "移动"
    },
    "1971255": {
        "province": "河南",
        "city": "新乡",
        "isp": "移动"
    },
    "1971256": {
        "province": "河南",
        "city": "新乡",
        "isp": "移动"
    },
    "1971258": {
        "province": "河南",
        "city": "新乡",
        "isp": "移动"
    },
    "1971261": {
        "province": "河南",
        "city": "周口",
        "isp": "移动"
    },
    "1971262": {
        "province": "河南",
        "city": "周口",
        "isp": "移动"
    },
    "1971263": {
        "province": "河南",
        "city": "周口",
        "isp": "移动"
    },
    "1971271": {
        "province": "河南",
        "city": "南阳",
        "isp": "移动"
    },
    "1971275": {
        "province": "河南",
        "city": "南阳",
        "isp": "移动"
    },
    "1971280": {
        "province": "河南",
        "city": "焦作",
        "isp": "移动"
    },
    "1971290": {
        "province": "河南",
        "city": "郑州",
        "isp": "移动"
    },
    "1971292": {
        "province": "河南",
        "city": "郑州",
        "isp": "移动"
    },
    "1971296": {
        "province": "河南",
        "city": "郑州",
        "isp": "移动"
    },
    "1971298": {
        "province": "河南",
        "city": "郑州",
        "isp": "移动"
    },
    "1971299": {
        "province": "河南",
        "city": "郑州",
        "isp": "移动"
    },
    "1971301": {
        "province": "河南",
        "city": "信阳",
        "isp": "移动"
    },
    "1971302": {
        "province": "河南",
        "city": "信阳",
        "isp": "移动"
    },
    "1971304": {
        "province": "山东",
        "city": "菏泽",
        "isp": "移动"
    },
    "1971306": {
        "province": "河南",
        "city": "信阳",
        "isp": "移动"
    },
    "1971308": {
        "province": "河南",
        "city": "许昌",
        "isp": "移动"
    },
    "1971309": {
        "province": "河南",
        "city": "许昌",
        "isp": "移动"
    },
    "1971310": {
        "province": "河北",
        "city": "承德",
        "isp": "移动"
    },
    "1971312": {
        "province": "河北",
        "city": "张家口",
        "isp": "移动"
    },
    "1971315": {
        "province": "河北",
        "city": "张家口",
        "isp": "移动"
    },
    "1971317": {
        "province": "河北",
        "city": "秦皇岛",
        "isp": "移动"
    },
    "1971322": {
        "province": "河南",
        "city": "开封",
        "isp": "移动"
    },
    "1971323": {
        "province": "河南",
        "city": "开封",
        "isp": "移动"
    },
    "1971325": {
        "province": "河南",
        "city": "开封",
        "isp": "移动"
    },
    "1971326": {
        "province": "河南",
        "city": "开封",
        "isp": "移动"
    },
    "1971330": {
        "province": "湖南",
        "city": "岳阳",
        "isp": "移动"
    },
    "1971331": {
        "province": "湖南",
        "city": "长沙",
        "isp": "移动"
    },
    "1971334": {
        "province": "湖南",
        "city": "衡阳",
        "isp": "移动"
    },
    "1971340": {
        "province": "山东",
        "city": "菏泽",
        "isp": "移动"
    },
    "1971341": {
        "province": "山东",
        "city": "济南",
        "isp": "移动"
    },
    "1971345": {
        "province": "山东",
        "city": "烟台",
        "isp": "移动"
    },
    "1971347": {
        "province": "山东",
        "city": "济宁",
        "isp": "移动"
    },
    "1971354": {
        "province": "山西",
        "city": "晋中",
        "isp": "移动"
    },
    "1971359": {
        "province": "山西",
        "city": "运城",
        "isp": "移动"
    },
    "1971366": {
        "province": "广西",
        "city": "百色",
        "isp": "移动"
    },
    "1971370": {
        "province": "河南",
        "city": "商丘",
        "isp": "移动"
    },
    "1971375": {
        "province": "河南",
        "city": "平顶山",
        "isp": "移动"
    },
    "1971377": {
        "province": "河南",
        "city": "南阳",
        "isp": "移动"
    },
    "1971381": {
        "province": "广西",
        "city": "贵港",
        "isp": "移动"
    },
    "1971382": {
        "province": "广西",
        "city": "崇左",
        "isp": "移动"
    },
    "1971386": {
        "province": "广西",
        "city": "玉林",
        "isp": "移动"
    },
    "1971387": {
        "province": "广西",
        "city": "钦州",
        "isp": "移动"
    },
    "1971398": {
        "province": "河南",
        "city": "三门峡",
        "isp": "移动"
    },
    "1971405": {
        "province": "山东",
        "city": "烟台",
        "isp": "移动"
    },
    "1971429": {
        "province": "河南",
        "city": "三门峡",
        "isp": "移动"
    },
    "1971439": {
        "province": "河南",
        "city": "信阳",
        "isp": "移动"
    },
    "1971440": {
        "province": "河南",
        "city": "信阳",
        "isp": "移动"
    },
    "1971442": {
        "province": "河南",
        "city": "周口",
        "isp": "移动"
    },
    "1971443": {
        "province": "河南",
        "city": "濮阳",
        "isp": "移动"
    },
    "1971450": {
        "province": "河南",
        "city": "郑州",
        "isp": "移动"
    },
    "1971451": {
        "province": "河南",
        "city": "郑州",
        "isp": "移动"
    },
    "1971454": {
        "province": "河南",
        "city": "郑州",
        "isp": "移动"
    },
    "1971465": {
        "province": "广西",
        "city": "百色",
        "isp": "移动"
    },
    "1971467": {
        "province": "广西",
        "city": "河池",
        "isp": "移动"
    },
    "1971472": {
        "province": "广西",
        "city": "来宾",
        "isp": "移动"
    },
    "1971484": {
        "province": "广西",
        "city": "崇左",
        "isp": "移动"
    },
    "1971504": {
        "province": "云南",
        "city": "红河",
        "isp": "移动"
    },
    "1971510": {
        "province": "江苏",
        "city": "无锡",
        "isp": "移动"
    },
    "1971511": {
        "province": "江苏",
        "city": "镇江",
        "isp": "移动"
    },
    "1971515": {
        "province": "江苏",
        "city": "盐城",
        "isp": "移动"
    },
    "1971516": {
        "province": "江苏",
        "city": "徐州",
        "isp": "移动"
    },
    "1971520": {
        "province": "广西",
        "city": "崇左",
        "isp": "移动"
    },
    "1971524": {
        "province": "云南",
        "city": "昭通",
        "isp": "移动"
    },
    "1971527": {
        "province": "江苏",
        "city": "宿迁",
        "isp": "移动"
    },
    "1971530": {
        "province": "山东",
        "city": "菏泽",
        "isp": "移动"
    },
    "1971539": {
        "province": "山东",
        "city": "临沂",
        "isp": "移动"
    },
    "1971540": {
        "province": "云南",
        "city": "昭通",
        "isp": "移动"
    },
    "1971541": {
        "province": "云南",
        "city": "昭通",
        "isp": "移动"
    },
    "1971542": {
        "province": "云南",
        "city": "昭通",
        "isp": "移动"
    },
    "1971544": {
        "province": "云南",
        "city": "昭通",
        "isp": "移动"
    },
    "1971545": {
        "province": "云南",
        "city": "昭通",
        "isp": "移动"
    },
    "1971547": {
        "province": "云南",
        "city": "昭通",
        "isp": "移动"
    },
    "1971548": {
        "province": "云南",
        "city": "昭通",
        "isp": "移动"
    },
    "1971549": {
        "province": "云南",
        "city": "昭通",
        "isp": "移动"
    },
    "1971552": {
        "province": "河南",
        "city": "郑州",
        "isp": "移动"
    },
    "1971553": {
        "province": "河南",
        "city": "郑州",
        "isp": "移动"
    },
    "1971555": {
        "province": "河南",
        "city": "郑州",
        "isp": "移动"
    },
    "1971558": {
        "province": "河南",
        "city": "郑州",
        "isp": "移动"
    },
    "1971561": {
        "province": "安徽",
        "city": "淮北",
        "isp": "移动"
    },
    "1971562": {
        "province": "安徽",
        "city": "淮北",
        "isp": "移动"
    },
    "1971564": {
        "province": "安徽",
        "city": "六安",
        "isp": "移动"
    },
    "1971565": {
        "province": "广西",
        "city": "河池",
        "isp": "移动"
    },
    "1971566": {
        "province": "安徽",
        "city": "宣城",
        "isp": "移动"
    },
    "1971567": {
        "province": "广西",
        "city": "钦州",
        "isp": "移动"
    },
    "1971571": {
        "province": "浙江",
        "city": "杭州",
        "isp": "移动"
    },
    "1971572": {
        "province": "浙江",
        "city": "湖州",
        "isp": "移动"
    },
    "1971581": {
        "province": "广西",
        "city": "玉林",
        "isp": "移动"
    },
    "1971584": {
        "province": "云南",
        "city": "昭通",
        "isp": "移动"
    },
    "1971586": {
        "province": "广西",
        "city": "桂林",
        "isp": "移动"
    },
    "1971614": {
        "province": "云南",
        "city": "昭通",
        "isp": "移动"
    },
    "1971617": {
        "province": "广西",
        "city": "百色",
        "isp": "移动"
    },
    "1971620": {
        "province": "广西",
        "city": "河池",
        "isp": "移动"
    },
    "1971624": {
        "province": "云南",
        "city": "昭通",
        "isp": "移动"
    },
    "1971629": {
        "province": "广西",
        "city": "钦州",
        "isp": "移动"
    },
    "1971632": {
        "province": "山东",
        "city": "枣庄",
        "isp": "移动"
    },
    "1971635": {
        "province": "山东",
        "city": "聊城",
        "isp": "移动"
    },
    "1971638": {
        "province": "广西",
        "city": "来宾",
        "isp": "移动"
    },
    "1971655": {
        "province": "云南",
        "city": "曲靖",
        "isp": "移动"
    },
    "1971658": {
        "province": "云南",
        "city": "曲靖",
        "isp": "移动"
    },
    "1971663": {
        "province": "广西",
        "city": "钦州",
        "isp": "移动"
    },
    "1971666": {
        "province": "云南",
        "city": "曲靖",
        "isp": "移动"
    },
    "1971667": {
        "province": "云南",
        "city": "曲靖",
        "isp": "移动"
    },
    "1971668": {
        "province": "云南",
        "city": "曲靖",
        "isp": "移动"
    },
    "1971673": {
        "province": "云南",
        "city": "文山",
        "isp": "移动"
    },
    "1971674": {
        "province": "云南",
        "city": "文山",
        "isp": "移动"
    },
    "1971675": {
        "province": "云南",
        "city": "文山",
        "isp": "移动"
    },
    "1971676": {
        "province": "云南",
        "city": "文山",
        "isp": "移动"
    },
    "1971677": {
        "province": "云南",
        "city": "文山",
        "isp": "移动"
    },
    "1971678": {
        "province": "云南",
        "city": "文山",
        "isp": "移动"
    },
    "1971679": {
        "province": "云南",
        "city": "文山",
        "isp": "移动"
    },
    "1971681": {
        "province": "云南",
        "city": "文山",
        "isp": "移动"
    },
    "1971698": {
        "province": "云南",
        "city": "临沧",
        "isp": "移动"
    },
    "1971699": {
        "province": "云南",
        "city": "临沧",
        "isp": "移动"
    },
    "1971702": {
        "province": "云南",
        "city": "临沧",
        "isp": "移动"
    },
    "1971710": {
        "province": "湖南",
        "city": "岳阳",
        "isp": "移动"
    },
    "1971711": {
        "province": "湖南",
        "city": "长沙",
        "isp": "移动"
    },
    "1971716": {
        "province": "四川",
        "city": "甘孜",
        "isp": "移动"
    },
    "1971731": {
        "province": "湖南",
        "city": "长沙",
        "isp": "移动"
    },
    "1971734": {
        "province": "湖南",
        "city": "衡阳",
        "isp": "移动"
    },
    "1971738": {
        "province": "湖南",
        "city": "娄底",
        "isp": "移动"
    },
    "1971746": {
        "province": "湖南",
        "city": "永州",
        "isp": "移动"
    },
    "1971756": {
        "province": "广东",
        "city": "茂名",
        "isp": "移动"
    },
    "1971778": {
        "province": "湖北",
        "city": "襄阳",
        "isp": "移动"
    },
    "1971780": {
        "province": "河北",
        "city": "唐山",
        "isp": "移动"
    },
    "1971793": {
        "province": "江西",
        "city": "上饶",
        "isp": "移动"
    },
    "1971794": {
        "province": "江西",
        "city": "抚州",
        "isp": "移动"
    },
    "1971797": {
        "province": "江西",
        "city": "赣州",
        "isp": "移动"
    },
    "1971801": {
        "province": "河北",
        "city": "廊坊",
        "isp": "移动"
    },
    "1971802": {
        "province": "河北",
        "city": "廊坊",
        "isp": "移动"
    },
    "1971805": {
        "province": "河北",
        "city": "保定",
        "isp": "移动"
    },
    "1971823": {
        "province": "河北",
        "city": "保定",
        "isp": "移动"
    },
    "1971832": {
        "province": "四川",
        "city": "绵阳",
        "isp": "移动"
    },
    "1971842": {
        "province": "河北",
        "city": "唐山",
        "isp": "移动"
    },
    "1971860": {
        "province": "河北",
        "city": "沧州",
        "isp": "移动"
    },
    "1971861": {
        "province": "河北",
        "city": "沧州",
        "isp": "移动"
    },
    "1971864": {
        "province": "河北",
        "city": "沧州",
        "isp": "移动"
    },
    "1971866": {
        "province": "河北",
        "city": "沧州",
        "isp": "移动"
    },
    "1971869": {
        "province": "安徽",
        "city": "淮南",
        "isp": "移动"
    },
    "1971870": {
        "province": "云南",
        "city": "昭通",
        "isp": "移动"
    },
    "1971872": {
        "province": "云南",
        "city": "大理",
        "isp": "移动"
    },
    "1971873": {
        "province": "云南",
        "city": "红河",
        "isp": "移动"
    },
    "1971874": {
        "province": "云南",
        "city": "曲靖",
        "isp": "移动"
    },
    "1971875": {
        "province": "云南",
        "city": "保山",
        "isp": "移动"
    },
    "1971876": {
        "province": "云南",
        "city": "文山",
        "isp": "移动"
    },
    "1971879": {
        "province": "云南",
        "city": "普洱",
        "isp": "移动"
    },
    "1971887": {
        "province": "安徽",
        "city": "六安",
        "isp": "移动"
    },
    "1971888": {
        "province": "安徽",
        "city": "六安",
        "isp": "移动"
    },
    "1971891": {
        "province": "安徽",
        "city": "宿州",
        "isp": "移动"
    },
    "1971893": {
        "province": "安徽",
        "city": "宿州",
        "isp": "移动"
    },
    "1971895": {
        "province": "安徽",
        "city": "宿州",
        "isp": "移动"
    },
    "1971897": {
        "province": "安徽",
        "city": "宿州",
        "isp": "移动"
    },
    "1971906": {
        "province": "新疆",
        "city": "奎屯",
        "isp": "移动"
    },
    "1971912": {
        "province": "陕西",
        "city": "榆林",
        "isp": "移动"
    },
    "1971914": {
        "province": "陕西",
        "city": "商洛",
        "isp": "移动"
    },
    "1971922": {
        "province": "安徽",
        "city": "合肥",
        "isp": "移动"
    },
    "1971923": {
        "province": "安徽",
        "city": "合肥",
        "isp": "移动"
    },
    "1971926": {
        "province": "安徽",
        "city": "合肥",
        "isp": "移动"
    },
    "1971927": {
        "province": "安徽",
        "city": "合肥",
        "isp": "移动"
    },
    "1971929": {
        "province": "安徽",
        "city": "合肥",
        "isp": "移动"
    },
    "1971931": {
        "province": "甘肃",
        "city": "兰州",
        "isp": "移动"
    },
    "1971936": {
        "province": "甘肃",
        "city": "张掖",
        "isp": "移动"
    },
    "1971950": {
        "province": "安徽",
        "city": "滁州",
        "isp": "移动"
    },
    "1971956": {
        "province": "安徽",
        "city": "滁州",
        "isp": "移动"
    },
    "1971959": {
        "province": "安徽",
        "city": "滁州",
        "isp": "移动"
    },
    "1971960": {
        "province": "安徽",
        "city": "阜阳",
        "isp": "移动"
    },
    "1971962": {
        "province": "安徽",
        "city": "阜阳",
        "isp": "移动"
    },
    "1971963": {
        "province": "安徽",
        "city": "阜阳",
        "isp": "移动"
    },
    "1971965": {
        "province": "安徽",
        "city": "阜阳",
        "isp": "移动"
    },
    "1971969": {
        "province": "安徽",
        "city": "阜阳",
        "isp": "移动"
    },
    "1971971": {
        "province": "内蒙古",
        "city": "呼和浩特",
        "isp": "移动"
    },
    "1971979": {
        "province": "内蒙古",
        "city": "锡林郭勒",
        "isp": "移动"
    },
    "1971983": {
        "province": "安徽",
        "city": "合肥",
        "isp": "移动"
    },
    "1971985": {
        "province": "安徽",
        "city": "合肥",
        "isp": "移动"
    },
    "1971986": {
        "province": "湖南",
        "city": "吉首",
        "isp": "移动"
    },
    "1971987": {
        "province": "湖南",
        "city": "衡阳",
        "isp": "移动"
    },
    "1971989": {
        "province": "湖南",
        "city": "长沙",
        "isp": "移动"
    },
    "1971990": {
        "province": "安徽",
        "city": "合肥",
        "isp": "移动"
    },
    "1971994": {
        "province": "湖南",
        "city": "衡阳",
        "isp": "移动"
    },
    "1972006": {
        "province": "湖北",
        "city": "黄石",
        "isp": "移动"
    },
    "1972007": {
        "province": "湖北",
        "city": "黄石",
        "isp": "移动"
    },
    "1972008": {
        "province": "湖北",
        "city": "黄石",
        "isp": "移动"
    },
    "1972011": {
        "province": "湖南",
        "city": "长沙",
        "isp": "移动"
    },
    "1972013": {
        "province": "湖南",
        "city": "株洲",
        "isp": "移动"
    },
    "1972016": {
        "province": "湖南",
        "city": "常德",
        "isp": "移动"
    },
    "1972018": {
        "province": "湖南",
        "city": "娄底",
        "isp": "移动"
    },
    "1972021": {
        "province": "上海",
        "city": "上海",
        "isp": "移动"
    },
    "1972024": {
        "province": "安徽",
        "city": "合肥",
        "isp": "移动"
    },
    "1972025": {
        "province": "江苏",
        "city": "南京",
        "isp": "移动"
    },
    "1972029": {
        "province": "陕西",
        "city": "西安",
        "isp": "移动"
    },
    "1972030": {
        "province": "湖南",
        "city": "岳阳",
        "isp": "移动"
    },
    "1972031": {
        "province": "河北",
        "city": "邢台",
        "isp": "移动"
    },
    "1972033": {
        "province": "河北",
        "city": "邢台",
        "isp": "移动"
    },
    "1972036": {
        "province": "湖南",
        "city": "常德",
        "isp": "移动"
    },
    "1972037": {
        "province": "河南",
        "city": "濮阳",
        "isp": "移动"
    },
    "1972041": {
        "province": "安徽",
        "city": "合肥",
        "isp": "移动"
    },
    "1972042": {
        "province": "安徽",
        "city": "合肥",
        "isp": "移动"
    },
    "1972043": {
        "province": "安徽",
        "city": "合肥",
        "isp": "移动"
    },
    "1972046": {
        "province": "安徽",
        "city": "阜阳",
        "isp": "移动"
    },
    "1972050": {
        "province": "湖南",
        "city": "岳阳",
        "isp": "移动"
    },
    "1972055": {
        "province": "安徽",
        "city": "合肥",
        "isp": "移动"
    },
    "1972056": {
        "province": "安徽",
        "city": "合肥",
        "isp": "移动"
    },
    "1972060": {
        "province": "湖南",
        "city": "长沙",
        "isp": "移动"
    },
    "1972061": {
        "province": "湖南",
        "city": "长沙",
        "isp": "移动"
    },
    "1972065": {
        "province": "湖南",
        "city": "郴州",
        "isp": "移动"
    },
    "1972067": {
        "province": "湖南",
        "city": "衡阳",
        "isp": "移动"
    },
    "1972073": {
        "province": "湖南",
        "city": "株洲",
        "isp": "移动"
    },
    "1972074": {
        "province": "湖南",
        "city": "张家界",
        "isp": "移动"
    },
    "1972075": {
        "province": "广东",
        "city": "湛江",
        "isp": "移动"
    },
    "1972077": {
        "province": "广西",
        "city": "来宾",
        "isp": "移动"
    },
    "1972079": {
        "province": "江西",
        "city": "上饶",
        "isp": "移动"
    },
    "1972091": {
        "province": "陕西",
        "city": "西安",
        "isp": "移动"
    },
    "1972098": {
        "province": "湖北",
        "city": "江汉",
        "isp": "移动"
    },
    "1972120": {
        "province": "湖北",
        "city": "十堰",
        "isp": "移动"
    },
    "1972121": {
        "province": "湖北",
        "city": "十堰",
        "isp": "移动"
    },
    "1972122": {
        "province": "湖北",
        "city": "十堰",
        "isp": "移动"
    },
    "1972123": {
        "province": "湖北",
        "city": "十堰",
        "isp": "移动"
    },
    "1972125": {
        "province": "湖北",
        "city": "十堰",
        "isp": "移动"
    },
    "1972136": {
        "province": "湖北",
        "city": "襄阳",
        "isp": "移动"
    },
    "1972144": {
        "province": "安徽",
        "city": "滁州",
        "isp": "移动"
    },
    "1972157": {
        "province": "江西",
        "city": "赣州",
        "isp": "移动"
    },
    "1972159": {
        "province": "江西",
        "city": "赣州",
        "isp": "移动"
    },
    "1972161": {
        "province": "江西",
        "city": "赣州",
        "isp": "移动"
    },
    "1972163": {
        "province": "江西",
        "city": "赣州",
        "isp": "移动"
    },
    "1972165": {
        "province": "江西",
        "city": "赣州",
        "isp": "移动"
    },
    "1972180": {
        "province": "陕西",
        "city": "西安",
        "isp": "移动"
    },
    "1972181": {
        "province": "陕西",
        "city": "西安",
        "isp": "移动"
    },
    "1972182": {
        "province": "陕西",
        "city": "西安",
        "isp": "移动"
    },
    "1972183": {
        "province": "陕西",
        "city": "西安",
        "isp": "移动"
    },
    "1972185": {
        "province": "陕西",
        "city": "西安",
        "isp": "移动"
    },
    "1972188": {
        "province": "陕西",
        "city": "西安",
        "isp": "移动"
    },
    "1972190": {
        "province": "广东",
        "city": "湛江",
        "isp": "移动"
    },
    "1972191": {
        "province": "陕西",
        "city": "西安",
        "isp": "移动"
    },
    "1972192": {
        "province": "陕西",
        "city": "西安",
        "isp": "移动"
    },
    "1972195": {
        "province": "陕西",
        "city": "西安",
        "isp": "移动"
    },
    "1972196": {
        "province": "陕西",
        "city": "西安",
        "isp": "移动"
    },
    "1972197": {
        "province": "陕西",
        "city": "西安",
        "isp": "移动"
    },
    "1972198": {
        "province": "陕西",
        "city": "西安",
        "isp": "移动"
    },
    "1972206": {
        "province": "贵州",
        "city": "黔南",
        "isp": "移动"
    },
    "1972207": {
        "province": "贵州",
        "city": "黔南",
        "isp": "移动"
    },
    "1972208": {
        "province": "贵州",
        "city": "黔南",
        "isp": "移动"
    },
    "1972209": {
        "province": "贵州",
        "city": "黔南",
        "isp": "移动"
    },
    "1972222": {
        "province": "湖南",
        "city": "长沙",
        "isp": "移动"
    },
    "1972225": {
        "province": "湖南",
        "city": "怀化",
        "isp": "移动"
    },
    "1972228": {
        "province": "湖南",
        "city": "长沙",
        "isp": "移动"
    },
    "1972229": {
        "province": "湖南",
        "city": "邵阳",
        "isp": "移动"
    },
    "1972251": {
        "province": "福建",
        "city": "厦门",
        "isp": "移动"
    },
    "1972252": {
        "province": "福建",
        "city": "厦门",
        "isp": "移动"
    },
    "1972253": {
        "province": "福建",
        "city": "厦门",
        "isp": "移动"
    },
    "1972254": {
        "province": "福建",
        "city": "厦门",
        "isp": "移动"
    },
    "1972256": {
        "province": "福建",
        "city": "厦门",
        "isp": "移动"
    },
    "1972271": {
        "province": "山西",
        "city": "晋中",
        "isp": "移动"
    },
    "1972273": {
        "province": "山西",
        "city": "太原",
        "isp": "移动"
    },
    "1972275": {
        "province": "山西",
        "city": "太原",
        "isp": "移动"
    },
    "1972301": {
        "province": "陕西",
        "city": "咸阳",
        "isp": "移动"
    },
    "1972303": {
        "province": "陕西",
        "city": "咸阳",
        "isp": "移动"
    },
    "1972305": {
        "province": "陕西",
        "city": "咸阳",
        "isp": "移动"
    },
    "1972308": {
        "province": "陕西",
        "city": "咸阳",
        "isp": "移动"
    },
    "1972332": {
        "province": "吉林",
        "city": "长春",
        "isp": "移动"
    },
    "1972336": {
        "province": "上海",
        "city": "上海",
        "isp": "移动"
    },
    "1972342": {
        "province": "四川",
        "city": "南充",
        "isp": "移动"
    },
    "1972357": {
        "province": "山西",
        "city": "临汾",
        "isp": "移动"
    },
    "1972360": {
        "province": "贵州",
        "city": "毕节",
        "isp": "移动"
    },
    "1972361": {
        "province": "贵州",
        "city": "毕节",
        "isp": "移动"
    },
    "1972362": {
        "province": "贵州",
        "city": "毕节",
        "isp": "移动"
    },
    "1972363": {
        "province": "贵州",
        "city": "毕节",
        "isp": "移动"
    },
    "1972365": {
        "province": "贵州",
        "city": "毕节",
        "isp": "移动"
    },
    "1972367": {
        "province": "贵州",
        "city": "毕节",
        "isp": "移动"
    },
    "1972370": {
        "province": "河南",
        "city": "商丘",
        "isp": "移动"
    },
    "1972371": {
        "province": "河南",
        "city": "郑州",
        "isp": "移动"
    },
    "1972372": {
        "province": "河南",
        "city": "安阳",
        "isp": "移动"
    },
    "1972373": {
        "province": "河南",
        "city": "新乡",
        "isp": "移动"
    },
    "1972378": {
        "province": "河南",
        "city": "开封",
        "isp": "移动"
    },
    "1972395": {
        "province": "河南",
        "city": "漯河",
        "isp": "移动"
    },
    "1972396": {
        "province": "河南",
        "city": "驻马店",
        "isp": "移动"
    },
    "1972403": {
        "province": "湖北",
        "city": "咸宁",
        "isp": "移动"
    },
    "1972431": {
        "province": "江西",
        "city": "赣州",
        "isp": "移动"
    },
    "1972463": {
        "province": "贵州",
        "city": "毕节",
        "isp": "移动"
    },
    "1972464": {
        "province": "贵州",
        "city": "毕节",
        "isp": "移动"
    },
    "1972511": {
        "province": "江苏",
        "city": "镇江",
        "isp": "移动"
    },
    "1972512": {
        "province": "江苏",
        "city": "苏州",
        "isp": "移动"
    },
    "1972515": {
        "province": "江苏",
        "city": "盐城",
        "isp": "移动"
    },
    "1972517": {
        "province": "江苏",
        "city": "淮安",
        "isp": "移动"
    },
    "1972523": {
        "province": "江苏",
        "city": "泰州",
        "isp": "移动"
    },
    "1972535": {
        "province": "山东",
        "city": "烟台",
        "isp": "移动"
    },
    "1972538": {
        "province": "山东",
        "city": "泰安",
        "isp": "移动"
    },
    "1972539": {
        "province": "山东",
        "city": "临沂",
        "isp": "移动"
    },
    "1972545": {
        "province": "福建",
        "city": "漳州",
        "isp": "移动"
    },
    "1972550": {
        "province": "湖北",
        "city": "襄阳",
        "isp": "移动"
    },
    "1972551": {
        "province": "湖北",
        "city": "孝感",
        "isp": "移动"
    },
    "1972552": {
        "province": "湖北",
        "city": "孝感",
        "isp": "移动"
    },
    "1972563": {
        "province": "安徽",
        "city": "阜阳",
        "isp": "移动"
    },
    "1972571": {
        "province": "浙江",
        "city": "杭州",
        "isp": "移动"
    },
    "1972573": {
        "province": "浙江",
        "city": "嘉兴",
        "isp": "移动"
    },
    "1972580": {
        "province": "浙江",
        "city": "舟山",
        "isp": "移动"
    },
    "1972584": {
        "province": "山西",
        "city": "太原",
        "isp": "移动"
    },
    "1972592": {
        "province": "福建",
        "city": "漳州",
        "isp": "移动"
    },
    "1972595": {
        "province": "福建",
        "city": "漳州",
        "isp": "移动"
    },
    "1972596": {
        "province": "福建",
        "city": "漳州",
        "isp": "移动"
    },
    "1972598": {
        "province": "福建",
        "city": "漳州",
        "isp": "移动"
    },
    "1972599": {
        "province": "福建",
        "city": "漳州",
        "isp": "移动"
    },
    "1972610": {
        "province": "福建",
        "city": "漳州",
        "isp": "移动"
    },
    "1972611": {
        "province": "福建",
        "city": "漳州",
        "isp": "移动"
    },
    "1972614": {
        "province": "山西",
        "city": "运城",
        "isp": "移动"
    },
    "1972624": {
        "province": "山西",
        "city": "吕梁",
        "isp": "移动"
    },
    "1972633": {
        "province": "山东",
        "city": "日照",
        "isp": "移动"
    },
    "1972655": {
        "province": "辽宁",
        "city": "丹东",
        "isp": "移动"
    },
    "1972686": {
        "province": "山西",
        "city": "吕梁",
        "isp": "移动"
    },
    "1972687": {
        "province": "山西",
        "city": "运城",
        "isp": "移动"
    },
    "1972688": {
        "province": "山西",
        "city": "运城",
        "isp": "移动"
    },
    "1972689": {
        "province": "山西",
        "city": "运城",
        "isp": "移动"
    },
    "1972690": {
        "province": "山西",
        "city": "运城",
        "isp": "移动"
    },
    "1972710": {
        "province": "湖北",
        "city": "孝感",
        "isp": "移动"
    },
    "1972711": {
        "province": "湖北",
        "city": "孝感",
        "isp": "移动"
    },
    "1972712": {
        "province": "湖北",
        "city": "孝感",
        "isp": "移动"
    },
    "1972713": {
        "province": "湖北",
        "city": "孝感",
        "isp": "移动"
    },
    "1972714": {
        "province": "湖北",
        "city": "孝感",
        "isp": "移动"
    },
    "1972739": {
        "province": "湖南",
        "city": "邵阳",
        "isp": "移动"
    },
    "1972744": {
        "province": "湖南",
        "city": "张家界",
        "isp": "移动"
    },
    "1972752": {
        "province": "广东",
        "city": "湛江",
        "isp": "移动"
    },
    "1972753": {
        "province": "广东",
        "city": "湛江",
        "isp": "移动"
    },
    "1972756": {
        "province": "广东",
        "city": "湛江",
        "isp": "移动"
    },
    "1972757": {
        "province": "广东",
        "city": "湛江",
        "isp": "移动"
    },
    "1972760": {
        "province": "广东",
        "city": "湛江",
        "isp": "移动"
    },
    "1972762": {
        "province": "广东",
        "city": "湛江",
        "isp": "移动"
    },
    "1972766": {
        "province": "广东",
        "city": "湛江",
        "isp": "移动"
    },
    "1972773": {
        "province": "天津",
        "city": "天津",
        "isp": "移动"
    },
    "1972774": {
        "province": "天津",
        "city": "天津",
        "isp": "移动"
    },
    "1972833": {
        "province": "四川",
        "city": "资阳",
        "isp": "移动"
    },
    "1972874": {
        "province": "云南",
        "city": "曲靖",
        "isp": "移动"
    },
    "1972883": {
        "province": "山西",
        "city": "运城",
        "isp": "移动"
    },
    "1972884": {
        "province": "山西",
        "city": "运城",
        "isp": "移动"
    },
    "1972912": {
        "province": "陕西",
        "city": "榆林",
        "isp": "移动"
    },
    "1972915": {
        "province": "陕西",
        "city": "汉中",
        "isp": "移动"
    },
    "1972916": {
        "province": "陕西",
        "city": "汉中",
        "isp": "移动"
    },
    "1972930": {
        "province": "甘肃",
        "city": "平凉",
        "isp": "移动"
    },
    "1972931": {
        "province": "甘肃",
        "city": "平凉",
        "isp": "移动"
    },
    "1972937": {
        "province": "吉林",
        "city": "长春",
        "isp": "移动"
    },
    "1972959": {
        "province": "上海",
        "city": "上海",
        "isp": "移动"
    },
    "1972967": {
        "province": "上海",
        "city": "上海",
        "isp": "移动"
    },
    "1972968": {
        "province": "上海",
        "city": "上海",
        "isp": "移动"
    },
    "1972974": {
        "province": "青海",
        "city": "海南",
        "isp": "移动"
    },
    "1972979": {
        "province": "内蒙古",
        "city": "锡林郭勒",
        "isp": "移动"
    },
    "1972982": {
        "province": "内蒙古",
        "city": "兴安",
        "isp": "移动"
    },
    "1972991": {
        "province": "吉林",
        "city": "长春",
        "isp": "移动"
    },
    "1972994": {
        "province": "上海",
        "city": "上海",
        "isp": "移动"
    },
    "1974082": {
        "province": "河北",
        "city": "保定",
        "isp": "移动"
    }
}